<?xml version="1.0" encoding="UTF-8"?> 
<java version="1.4.0_01" class="java.beans.XMLDecoder"> 
 <object class="burningbox.org.dsh.entities.magic.Spell"> 
  <void property="castingTime"> 
   <string>1 action</string> 
  </void> 
  <void property="classes"> 
   <void method="add"> 
    <object class="burningbox.org.dsh.entities.ClassLevel"> 
     <void property="className"> 
      <string>adp</string> 
     </void> 
     <void property="levelReached"> 
      <int>2</int> 
     </void> 
    </object> 
   </void> 
   <void method="add"> 
    <object class="burningbox.org.dsh.entities.ClassLevel"> 
     <void property="className"> 
      <string>brd</string> 
     </void> 
     <void property="levelReached"> 
      <int>2</int> 
     </void> 
    </object> 
   </void> 
   <void method="add"> 
    <object class="burningbox.org.dsh.entities.ClassLevel"> 
     <void property="className"> 
      <string>sor</string> 
     </void> 
     <void property="levelReached"> 
      <int>2</int> 
     </void> 
    </object> 
   </void> 
   <void method="add"> 
    <object class="burningbox.org.dsh.entities.ClassLevel"> 
     <void property="className"> 
      <string>wiz</string> 
     </void> 
     <void property="levelReached"> 
      <int>2</int> 
     </void> 
    </object> 
   </void> 
  </void> 
  <void property="components"> 
   <void method="add"> 
    <string>V</string> 
   </void> 
   <void method="add"> 
    <string>S</string> 
   </void> 
   <void method="add"> 
    <string>M</string> 
   </void> 
  </void> 
  <void property="description"> 
   <string>Reveals invisible creatures or objects.</string> 
  </void> 
  <void property="duration"> 
   <string>10 minutes/level (D)</string> 
  </void> 
  <void property="longDescription"> 
   <string>
You see any objects or beings that are invisible, as well as
any that are astral or ethereal, as if they were normally
visible.
The spell does not reveal the method used to obtain
invisibility, though an astral traveler is easy to identify if he
has a silver cord. It does not reveal illusions or enable you to
see through opaque objects. It does not reveal creatures who are
simply hiding, concealed, or otherwise hard to see.
</string> 
  </void> 
  <void property="name"> 
   <string>See Invisibility</string> 
  </void> 
  <void property="range"> 
   <string>Medium (100 ft. + 10 ft./level)</string> 
  </void> 
  <void property="savingThrow"> 
   <string>None</string> 
  </void> 
  <void property="school"> 
   <string>Divination</string> 
  </void> 
  <void property="spellResistance"> 
   <string>No</string> 
  </void> 
 </object> 
</java> 
